llq/__init__.py
llq/util/__init__.py
llq/util/data/__init__.py
llq/util/data/fakeData.py
llq/util/devices/GPU.py
llq/util/devices/__init__.py
llq/util/network/__init__.py
llq/util/network/wifi.py
llq_data-0.8.1.dist-info/METADATA
llq_data-0.8.1.dist-info/WHEEL
llq_data-0.8.1.dist-info/top_level.txt
llq_data-0.8.1.dist-info/RECORD
